ednoflow/__init__.py
ednoflow/core/__init__.py
ednoflow/core/agent.py
ednoflow/core/edge.py
ednoflow/core/network.py
ednoflow/core/node.py
ednoflow-0.0.2.dist-info/LICENSE
ednoflow-0.0.2.dist-info/METADATA
ednoflow-0.0.2.dist-info/WHEEL
ednoflow-0.0.2.dist-info/top_level.txt
ednoflow-0.0.2.dist-info/RECORD
